tce/__init__.py
tce/calculator.py
tce/constants.py
tce/datasets.py
tce/monte_carlo.py
tce/structures.py
tce/topology.py
tce/training.py
tce/datasets/cantor_alloy_surrogate/configuration_0.xyz
tce/datasets/cantor_alloy_surrogate/configuration_1.xyz
tce/datasets/cantor_alloy_surrogate/configuration_10.xyz
tce/datasets/cantor_alloy_surrogate/configuration_100.xyz
tce/datasets/cantor_alloy_surrogate/configuration_101.xyz
tce/datasets/cantor_alloy_surrogate/configuration_102.xyz
tce/datasets/cantor_alloy_surrogate/configuration_103.xyz
tce/datasets/cantor_alloy_surrogate/configuration_104.xyz
tce/datasets/cantor_alloy_surrogate/configuration_105.xyz
tce/datasets/cantor_alloy_surrogate/configuration_106.xyz
tce/datasets/cantor_alloy_surrogate/configuration_107.xyz
tce/datasets/cantor_alloy_surrogate/configuration_108.xyz
tce/datasets/cantor_alloy_surrogate/configuration_109.xyz
tce/datasets/cantor_alloy_surrogate/configuration_11.xyz
tce/datasets/cantor_alloy_surrogate/configuration_110.xyz
tce/datasets/cantor_alloy_surrogate/configuration_111.xyz
tce/datasets/cantor_alloy_surrogate/configuration_112.xyz
tce/datasets/cantor_alloy_surrogate/configuration_113.xyz
tce/datasets/cantor_alloy_surrogate/configuration_114.xyz
tce/datasets/cantor_alloy_surrogate/configuration_115.xyz
tce/datasets/cantor_alloy_surrogate/configuration_116.xyz
tce/datasets/cantor_alloy_surrogate/configuration_117.xyz
tce/datasets/cantor_alloy_surrogate/configuration_118.xyz
tce/datasets/cantor_alloy_surrogate/configuration_119.xyz
tce/datasets/cantor_alloy_surrogate/configuration_12.xyz
tce/datasets/cantor_alloy_surrogate/configuration_120.xyz
tce/datasets/cantor_alloy_surrogate/configuration_121.xyz
tce/datasets/cantor_alloy_surrogate/configuration_122.xyz
tce/datasets/cantor_alloy_surrogate/configuration_123.xyz
tce/datasets/cantor_alloy_surrogate/configuration_124.xyz
tce/datasets/cantor_alloy_surrogate/configuration_125.xyz
tce/datasets/cantor_alloy_surrogate/configuration_126.xyz
tce_lib-0.10.3.dist-info/METADATA
tce_lib-0.10.3.dist-info/WHEEL
tce_lib-0.10.3.dist-info/licenses/LICENSE
tce_lib-0.10.3.dist-info/RECORD
