Metadata-Version: 2.4
Name: tce-lib
Version: 0.10.3
Summary: tensor cluster expansion library for solid solution modeling
Project-URL: Homepage, https://github.com/MUEXLY/tce-lib
License-Expression: MIT
License-File: LICENSE
Keywords: alloys,ase,cluster expansion,density functional theory,machine learning,materials science,monte carlo,scientific computing
Classifier: Development Status :: 3 - Alpha
Classifier: Intended Audience :: Science/Research
Classifier: Programming Language :: Python :: 3.10
Classifier: Programming Language :: Python :: 3.11
Classifier: Programming Language :: Python :: 3.12
Classifier: Topic :: Scientific/Engineering :: Chemistry
Classifier: Topic :: Scientific/Engineering :: Physics
Requires-Python: >=3.10
Requires-Dist: aenum<3.1.17,>=3.0.0
Requires-Dist: ase<3.26.0,>=3.10.0
Requires-Dist: numpy<3.0,>=2.0.0
Requires-Dist: opt-einsum<4.0,>=3.0.1
Requires-Dist: scipy<1.16.0,>=1.6.0
Requires-Dist: sparse<0.17.0,>=0.14.0
Provides-Extra: dev
Requires-Dist: hatchling~=1.27.0; extra == 'dev'
Requires-Dist: mypy~=1.13.0; extra == 'dev'
Requires-Dist: pdoc~=15.0.1; extra == 'dev'
Requires-Dist: pytest-cov~=7.0.0; extra == 'dev'
Requires-Dist: pytest~=8.0.2; extra == 'dev'
Requires-Dist: ruff~=0.9.4; extra == 'dev'
Requires-Dist: scikit-learn~=1.7.1; extra == 'dev'
Requires-Dist: scipy-stubs~=1.15.3.0; extra == 'dev'
Provides-Extra: examples
Requires-Dist: cowley-sro-parameters~=1.1.1; extra == 'examples'
Requires-Dist: ovito~=3.13.1; extra == 'examples'
Requires-Dist: requests~=2.32.5; extra == 'examples'
Requires-Dist: scikit-learn~=1.7.1; extra == 'examples'
